{
"type": "FeatureCollection",
"name": "TERMINAL_TYPE_B_PT",
"crs": { "type": "name", "properties": { "name": "urn:ogc:def:crs:OGC:1.3:CRS84" } },
"features": [
{ "type": "Feature", "properties": { "JENIS": "SISTEM TRANSPORTASI", "TOPONIMI": "TERMINAL B CIBEBER/SERUNI", "KETERANGAN": "TERMINAL", "X": "106,084099184", "Y": "-6,02171984599994" }, "geometry": { "type": "Point", "coordinates": [ 106.084099184000081, -6.021719845999938, 0.0 ] } }
]
}
